Metadata-Version: 1.1
Name: fio-amazon-mws
Version: 3.4.14.3
Summary: Amazon MWS Integration
Home-page: http://www.fulfil.io/
Author: Fulfil.IO Inc., Openlabs Technologies and Consulting P Ltd.
Author-email: UNKNOWN
License: BSD
Download-URL: https://github.com/fulfilio/trytond-amazon-mws
Platform: UNKNOWN
Classifier: Development Status :: 4 - Beta
Classifier: Environment :: Plugins
Classifier: Framework :: Tryton
Classifier: Intended Audience :: Developers
Classifier: Intended Audience :: Financial and Insurance Industry
Classifier: Intended Audience :: Legal Industry
Classifier: Intended Audience :: Manufacturing
Classifier: License :: OSI Approved :: BSD License
Classifier: Natural Language :: English
Classifier: Operating System :: OS Independent
Classifier: Programming Language :: Python :: 2.7
Classifier: Topic :: Office/Business
